aslem/__init__.py
aslem-0.0.1.dist-info/METADATA
aslem-0.0.1.dist-info/RECORD
aslem-0.0.1.dist-info/WHEEL
aslem-0.0.1.dist-info/top_level.txt
