Metadata-Version: 2.1
Name: aslem
Version: 0.0.1
Summary: A lightweight experiment manager based on Linux's screen utility.
Home-page: https://github.com/StanfordASL/aslem
Author: Boris Ivanovic
Author-email: borisi@stanford.edu
License: UNKNOWN
Platform: UNKNOWN
Classifier: Programming Language :: Python :: 3
Classifier: License :: OSI Approved :: MIT License
Classifier: Operating System :: OS Independent
